animalia/__init__.py
animalia/cli.py
animalia/load_data.py
animalia/species_name_generator.py
animalia/animalia.egg-info/PKG-INFO
animalia/animalia.egg-info/SOURCES.txt
animalia/animalia.egg-info/dependency_links.txt
animalia/animalia.egg-info/entry_points.txt
animalia/animalia.egg-info/requires.txt
animalia/animalia.egg-info/top_level.txt
animalia/data/species.txt
animalia-0.0.28.dist-info/LICENSE
animalia-0.0.28.dist-info/METADATA
animalia-0.0.28.dist-info/WHEEL
animalia-0.0.28.dist-info/entry_points.txt
animalia-0.0.28.dist-info/top_level.txt
animalia-0.0.28.dist-info/RECORD
