Metadata-Version: 2.1
Name: animalia
Version: 0.0.28
Summary: Animalia is a Python package that generates species data for you
Home-page: https://pypi.org/project/animalia
Author: Gigaquads
Author-email: what@gigaquads.com
License: UNKNOWN
Platform: UNKNOWN
Classifier: Programming Language :: Python :: 3.9
Requires-Dist: appyratus
